dircast.py
dircast-0.2.dist-info/RECORD
dircast-0.2.dist-info/DESCRIPTION.rst
dircast-0.2.dist-info/top_level.txt
dircast-0.2.dist-info/WHEEL
dircast-0.2.dist-info/metadata.json
dircast-0.2.dist-info/METADATA
