Metadata-Version: 2.0
Name: dircast
Version: 0.2
Summary: Tool for duplicate directories search.
Home-page: UNKNOWN
Author: Dmitry Unruh
Author-email: dmitryunruh@googlemail.com
License: MIT
Keywords: search find duplicate directories folders
Platform: UNKNOWN
Classifier: Development Status :: 3 - Alpha
Classifier: License :: OSI Approved :: MIT License
Classifier: Environment :: Console
Classifier: Operating System :: OS Independent
Classifier: Programming Language :: Python :: 3
Classifier: Programming Language :: Python :: 3.4
